worldcup18/__init__.py
worldcup18/api_parser.py
worldcup18/utils.py
worldcup18/worldcup.py
worldcup18-0.1.1.dist-info/entry_points.txt
worldcup18-0.1.1.dist-info/LICENSE
worldcup18-0.1.1.dist-info/WHEEL
worldcup18-0.1.1.dist-info/METADATA
worldcup18-0.1.1.dist-info/RECORD
