Metadata-Version: 2.1
Name: worldcup18
Version: 0.1.1
Summary: A simple CLI to stay up to date with 2018 World Cup
Home-page: https://github.com/tadeoos/worldcup
License: MIT
Keywords: worldcup,cli,fifa
Author: Tadek Teleżyński
Author-email: tadekte@gmail.com
Requires-Python: >=2.7, !=3.0.*, !=3.1.*, !=3.2.*, !=3.3.*
Classifier: License :: OSI Approved :: MIT License
Classifier: Programming Language :: Python :: 2
Classifier: Programming Language :: Python :: 2.7
Classifier: Programming Language :: Python :: 3
Classifier: Programming Language :: Python :: 3.4
Classifier: Programming Language :: Python :: 3.5
Classifier: Programming Language :: Python :: 3.6
Classifier: Programming Language :: Python :: 3.7
Requires-Dist: click (>=6.7,<7.0)
Requires-Dist: python-dateutil (>=2.7,<3.0)
Requires-Dist: pytz (>=2018.4,<2019.0)
Requires-Dist: requests (>=2.19,<3.0)
Requires-Dist: tzlocal (>=1.5,<2.0)
